s1ard/__init__.py
s1ard/ancillary.py
s1ard/ard.py
s1ard/cli.py
s1ard/config.py
s1ard/etad.py
s1ard/ocn.py
s1ard/processor.py
s1ard/search.py
s1ard/snap.py
s1ard/metadata/__init__.py
s1ard/metadata/extract.py
s1ard/metadata/mapping.py
s1ard/metadata/stac.py
s1ard/processors/__init__.py
s1ard/processors/base.py
s1ard/processors/registry.py
s1ard/processors/snap.py
s1ard/resources/config.ini
s1ard/validation/validate_cog.py
s1ard/validation/validate_xml.py
s1ard/validation/schemas/product.xsd
s1ard/validation/schemas/source.xsd
s1ard-2.10.1.dist-info/licenses/LICENSE.txt
s1ard-2.10.1.dist-info/METADATA
s1ard-2.10.1.dist-info/WHEEL
s1ard-2.10.1.dist-info/entry_points.txt
s1ard-2.10.1.dist-info/top_level.txt
s1ard-2.10.1.dist-info/RECORD
