Metadata-Version: 2.4
Name: s1ard
Version: 2.10.1
Summary: A prototype processor for Sentinel-1 Analysis Ready Data (ARD) backscatter products
Maintainer-email: John Truckenbrodt <john.truckenbrodt@dlr.de>
License: # Copyright (c) 2021-2026, Marco Wolsza and John Truckenbrodt.
Project-URL: repository, https://github.com/SAR-ARD/s1ard
Project-URL: documentation, https://s1ard.readthedocs.io/en/latest/
Classifier: License :: OSI Approved :: MIT License
Classifier: Operating System :: Microsoft :: Windows
Classifier: Operating System :: POSIX :: Linux
Classifier: Programming Language :: Python :: 3
Requires-Python: >=3.10
License-File: LICENSE.txt
Requires-Dist: asf_search
Requires-Dist: cesard>=1.2.1
Requires-Dist: click>=7.1.0
Requires-Dist: gdal>=3.5.0
Requires-Dist: geopandas
Requires-Dist: lxml
Requires-Dist: multiformats>=0.3.1
Requires-Dist: numpy<2.0
Requires-Dist: packaging
Requires-Dist: pandas
Requires-Dist: pyproj
Requires-Dist: pyroSAR>=0.33.2
Requires-Dist: pystac<1.11.0,>=1.8.0
Requires-Dist: pystac-client>=0.7.0
Requires-Dist: python-dateutil
Requires-Dist: requests
Requires-Dist: s1etad>=0.5.3
Requires-Dist: s1etad_tools>=0.8.1
Requires-Dist: scipy
Requires-Dist: shapely
Requires-Dist: spatialist>=0.16.0
Provides-Extra: test
Requires-Dist: pytest; extra == "test"
Requires-Dist: requests; extra == "test"
Provides-Extra: docs
Requires-Dist: sphinx; extra == "docs"
Requires-Dist: sphinxcontrib-bibtex; extra == "docs"
Requires-Dist: nbsphinx; extra == "docs"
Requires-Dist: sphinx_rtd_theme; extra == "docs"
Requires-Dist: sphinx-toolbox; extra == "docs"
Requires-Dist: ipython; extra == "docs"
Dynamic: license-file
